pysspm/__init__.py
pysspm/cli/__init__.py
pysspm/cli/cli_config.py
pysspm/cli/cli_init.py
pysspm/cli/cli_project.py
pysspm/cli/cli_stats.py
pysspm/lib/__init__.py
pysspm/lib/config.py
pysspm/lib/metadata.py
pysspm/lib/project.py
pysspm/lib/stats.py
pysspm/lib/util.py
pysspm/sspm.py
pysspm-0.2.1.dist-info/WHEEL
pysspm-0.2.1.dist-info/METADATA
pysspm-0.2.1.dist-info/entry_points.txt
pysspm-0.2.1.dist-info/RECORD
