Metadata-Version: 2.1
Name: pysspm
Version: 0.2.1
Summary: Simple Scientific Project Manager.
Home-page: https://github.com/aarpon/pysspm
License: Apache-2.0
Author: Aaron Ponti
Author-email: aaron.ponti@bsse.ethz.ch
Requires-Python: >=3.10,<4.0
Classifier: License :: OSI Approved :: Apache Software License
Classifier: Programming Language :: Python :: 3
Classifier: Programming Language :: Python :: 3.10
Classifier: Programming Language :: Python :: 3.11
Requires-Dist: colorama (>=0.4.4,<0.5.0)
Requires-Dist: pandas (>=1.5.0,<2.0.0)
Requires-Dist: tabulate (>=0.8.10,<0.9.0)
Requires-Dist: typer (>=0.4.1,<0.5.0)
Project-URL: Documentation, https://github.com/aarpon/pysspm
Project-URL: Repository, https://github.com/aarpon/pysspm
